celery_queued_once-0.2.dist-info/DESCRIPTION.rst
celery_queued_once-0.2.dist-info/METADATA
celery_queued_once-0.2.dist-info/metadata.json
celery_queued_once-0.2.dist-info/RECORD
celery_queued_once-0.2.dist-info/top_level.txt
celery_queued_once-0.2.dist-info/WHEEL
queued_once/__init__.py
queued_once/task.py
queued_once/tests.py
