Metadata-Version: 2.0
Name: celery-queued-once
Version: 0.2
Summary: Celery base task de-duplicating tasks
Home-page: UNKNOWN
Author: Educreations Engineering
Author-email: UNKNOWN
License: UNKNOWN
Platform: UNKNOWN
Requires-Dist: celery
Requires-Dist: django (>=1.7)
